{"classifier":{"classFeatures":{"menu_dich_vu":{"0":2,"1":4,"2":12,"3":12,"4":3,"5":3,"6":6,"7":6,"8":5,"9":4,"10":3,"11":3,"12":2,"13":2,"14":2,"15":2,"16":2,"17":4,"18":2,"19":2,"20":2},"nang_nguc":{"10":2,"11":2,"12":3,"18":2,"21":7,"22":11,"23":2,"24":3,"25":2,"26":2,"27":2,"28":3,"29":3,"30":2,"31":2,"32":4,"33":2,"34":2,"35":2,"36":2,"37":2,"38":2,"39":2,"40":2,"41":2},"nang_mui":{"6":2,"9":2,"10":4,"11":4,"12":3,"18":4,"21":13,"24":3,"25":3,"26":4,"27":4,"28":3,"29":3,"42":23,"43":3,"44":5,"45":3,"46":3,"47":2,"48":3,"49":3,"50":2,"51":2,"52":2,"58":3,"83":2,"84":2,"134":2},"tham_my_mat":{"10":4,"11":4,"26":2,"27":2,"29":2,"44":2,"47":2,"49":2,"53":3,"54":6,"55":9,"56":2,"57":2,"58":3,"59":2,"60":2,"61":2,"62":2,"63":2,"64":2,"81":2,"82":2,"84":2,"94":2},"tham_my_cam":{"6":2,"47":2,"50":2,"65":7,"66":2,"67":2},"cang_da":{"6":2,"30":2,"55":3,"56":2,"59":2,"68":5,"69":7,"70":2,"71":2,"72":2,"73":2,"135":3,"136":5},"hoi_gia":{"14":2,"20":2,"23":4,"24":2,"25":2,"26":2,"27":2,"30":2,"31":3,"74":2},"dat_lich":{"10":9,"11":9,"18":6,"30":7,"75":9,"76":4,"77":6,"78":2,"79":2,"80":3,"81":2,"82":2,"83":4,"84":10,"85":7,"86":9,"87":9,"88":6,"89":4,"90":3,"91":3,"92":2,"93":2,"94":2,"95":3,"96":13,"97":11,"98":2,"99":3},"dia_chi":{"11":2,"28":5,"30":4,"77":8,"81":2,"82":2,"83":2,"92":3,"100":8,"101":4,"102":2,"103":2,"104":2,"105":3},"hut_mo":{"12":2,"26":2,"27":2,"28":2,"29":3,"106":7,"107":9,"108":3,"109":4,"110":2,"111":2,"112":2,"113":2,"114":2,"115":2,"116":2},"tham_my_vung_kin":{"6":2,"9":2,"10":2,"11":2,"26":2,"27":2,"48":2,"117":2,"118":2,"119":6,"120":6,"121":2,"122":2},"xem_feedback":{"0":2,"6":2,"9":2,"122":3,"123":4,"124":4,"125":3,"126":2,"127":2,"128":3,"129":3,"130":2,"131":2,"132":2,"133":2},"bien_chung":{"12":2,"17":4,"49":14,"51":4,"52":4,"117":4,"127":2,"135":15,"136":16,"137":7,"138":2,"139":2,"140":4,"141":4},"treo_sa_tre":{"62":5,"117":3,"136":10,"137":5,"141":3,"142":9,"143":7},"faq_thao_tui":{"28":2,"136":3,"138":3,"141":2},"faq_nang_nguc_dao":{"28":2,"82":2,"136":3,"141":2,"144":2},"faq_nguc_bay":{"127":4,"136":4,"145":3,"146":2,"147":2}},"classTotals":{"menu_dich_vu":21,"nang_nguc":11,"nang_mui":23,"tham_my_mat":13,"tham_my_cam":7,"cang_da":11,"hoi_gia":6,"dat_lich":42,"dia_chi":10,"hut_mo":10,"tham_my_vung_kin":6,"xem_feedback":8,"bien_chung":29,"treo_sa_tre":13,"faq_thao_tui":3,"faq_nang_nguc_dao":3,"faq_nguc_bay":4},"totalExamples":204,"smoothing":1},"docs":[{"label":"menu_dich_vu","text":["xem","cac","dich","vu"]},{"label":"menu_dich_vu","text":["menu","dich","vu"]},{"label":"menu_dich_vu","text":["cac","dich","vu","khac"]},{"label":"menu_dich_vu","text":["dich","vu","lam","ep"]},{"label":"menu_dich_vu","text":["dv","lam","ep"]},{"label":"menu_dich_vu","text":["dich","vu","tham"]},{"label":"menu_dich_vu","text":["tu","van","dich","vu"]},{"label":"menu_dich_vu","text":["co","nhung","dich","vu","nao"]},{"label":"menu_dich_vu","text":["danh","sach","dich","vu"]},{"label":"menu_dich_vu","text":["dich","vu","gi"]},{"label":"menu_dich_vu","text":["tham","gi"]},{"label":"menu_dich_vu","text":["lam","ep","gi"]},{"label":"menu_dich_vu","text":["menu"]},{"label":"menu_dich_vu","text":["dich","vu"]},{"label":"menu_dich_vu","text":["tu","van","lam","ep"]},{"label":"menu_dich_vu","text":["muon","lam","ep"]},{"label":"menu_dich_vu","text":["dv","tham"]},{"label":"menu_dich_vu","text":["dv","khac"]},{"label":"menu_dich_vu","text":["cac","dv"]},{"label":"menu_dich_vu","text":["tat","ca","dich","vu"]},{"label":"nang_nguc","text":["tu","van","nang","nguc"]},{"label":"nang_nguc","text":["nang","nguc","gia","bao","nhieu"]},{"label":"nang_nguc","text":["phau","thuat","nguc","co","au","khong"]},{"label":"nang_nguc","text":["muon","nang","nguc"]},{"label":"nang_nguc","text":["chi","phi","tui","nguc"]},{"label":"nang_nguc","text":["nang","nguc","au","tot"]},{"label":"nang_nguc","text":["nang","nguc","co","lai","seo","khong"]},{"label":"nang_nguc","text":["nang","nguc","bao","lau","thi","lanh"]},{"label":"nang_nguc","text":["thao","tui","nguc","cu"]},{"label":"nang_nguc","text":["thai","tui","nguc"]},{"label":"nang_mui","text":["nang","mui","het","bao","nhieu"]},{"label":"nang_mui","text":["tu","van","nang","mui"]},{"label":"nang_mui","text":["phau","thuat","mui"]},{"label":"nang_mui","text":["muon","sua","mui"]},{"label":"nang_mui","text":["nang","mui","sun","suon"]},{"label":"nang_mui","text":["nang","mui","co","au","khong"]},{"label":"nang_mui","text":["chinh","sua","mui","hong"]},{"label":"nang_mui","text":["mui","bi","lech"]},{"label":"nang_mui","text":["mui","bi","bien","chung"]},{"label":"nang_mui","text":["sua","mui","hong"]},{"label":"tham_my_mat","text":["cat","mi","mat"]},{"label":"tham_my_mat","text":["nhan","mi"]},{"label":"tham_my_mat","text":["bam","mi"]},{"label":"tham_my_mat","text":["tu","van","ve","mat"]},{"label":"tham_my_mat","text":["phau","thuat","mat"]},{"label":"tham_my_mat","text":["mat","bi","xe"]},{"label":"tham_my_mat","text":["mat","mot","mi"]},{"label":"tham_my_mat","text":["mat","khong","eu"]},{"label":"tham_my_mat","text":["treo","cung","mai"]},{"label":"tham_my_mat","text":["chinh","sua","mat"]},{"label":"tham_my_cam","text":["cam"]},{"label":"tham_my_cam","text":["cam"]},{"label":"tham_my_cam","text":["cam","ngan"]},{"label":"tham_my_cam","text":["cam","lech"]},{"label":"tham_my_cam","text":["chinh","cam"]},{"label":"tham_my_cam","text":["lam","cam","vline"]},{"label":"cang_da","text":["cang","da","mat"]},{"label":"cang_da","text":["tre","hoa","da"]},{"label":"cang_da","text":["cang","chi"]},{"label":"cang_da","text":["cang","da","chai","xe"]},{"label":"cang_da","text":["xoa","nhan"]},{"label":"cang_da","text":["lam","cang","da","mat"]},{"label":"hoi_gia","text":["gia","bao","nhieu"]},{"label":"hoi_gia","text":["chi","phi"]},{"label":"hoi_gia","text":["bang","gia"]},{"label":"hoi_gia","text":["phi","phau","thuat"]},{"label":"hoi_gia","text":["gia","ca","nao"]},{"label":"dat_lich","text":["lich"]},{"label":"dat_lich","text":["hen","kham"]},{"label":"dat_lich","text":["ang","ky","tu","van"]},{"label":"dat_lich","text":["muon","gap","bac","si"]},{"label":"dat_lich","text":["lich","kham"]},{"label":"dat_lich","text":["cho","em","xin","ien","thoai"]},{"label":"dat_lich","text":["xin","zalo"]},{"label":"dat_lich","text":["xin","viber"]},{"label":"dat_lich","text":["muon","tu","van"]},{"label":"dat_lich","text":["tu","van","truc","tiep"]},{"label":"dat_lich","text":["gap","truc","tiep"]},{"label":"dat_lich","text":["muon","en","kham"]},{"label":"dat_lich","text":["hen"]},{"label":"dat_lich","text":["xin","ien","thoai","tu","van"]},{"label":"dat_lich","text":["muon","uoc","tu","van"]},{"label":"dat_lich","text":["tu","van"]},{"label":"dat_lich","text":["tu","van","giup","em"]},{"label":"dat_lich","text":["cho","em","lich"]},{"label":"dat_lich","text":["muon","book","lich"]},{"label":"dat_lich","text":["book","lich","kham"]},{"label":"dat_lich","text":["lich"]},{"label":"dat_lich","text":["hen"]},{"label":"dat_lich","text":["lich","kham"]},{"label":"dat_lich","text":["lich","tu","van"]},{"label":"dat_lich","text":["xin","ien","thoai"]},{"label":"dat_lich","text":["cho","xin","ien","thoai"]},{"label":"dat_lich","text":["ien","thoai","cua","chi","la"]},{"label":"dat_lich","text":["ien","thoai","cua","em","la"]},{"label":"dat_lich","text":["cua","chi","la"]},{"label":"dat_lich","text":["cua","em","la"]},{"label":"dat_lich","text":["ien","thoai"]},{"label":"dat_lich","text":["sdt"]},{"label":"dat_lich","text":["ien","thoai"]},{"label":"dat_lich","text":["ay","la","cua","chi"]},{"label":"dat_lich","text":["ay","la","cua","em"]},{"label":"dat_lich","text":["zalo","cua","chi","la"]},{"label":"dat_lich","text":["zalo","cua","em","la"]},{"label":"dat_lich","text":["zalo","cua","chi"]},{"label":"dat_lich","text":["zalo","cua","em"]},{"label":"dat_lich","text":["viber","cua","chi","la"]},{"label":"dat_lich","text":["viber","cua","em","la"]},{"label":"dia_chi","text":["phong","kham","au"]},{"label":"dia_chi","text":["ia","chi","phong","kham"]},{"label":"dia_chi","text":["cho","kham","au"]},{"label":"dia_chi","text":["ia","iem","phong","kham"]},{"label":"dia_chi","text":["van","phong","au"]},{"label":"dia_chi","text":["ia","chi","bac","si"]},{"label":"dia_chi","text":["phong","kham","nam","au"]},{"label":"dia_chi","text":["tim","uong","en","phong","kham"]},{"label":"dia_chi","text":["chi","uong","en","phong","kham"]},{"label":"hut_mo","text":["hut","mo","bung"]},{"label":"hut_mo","text":["giam","mo","bung"]},{"label":"hut_mo","text":["hut","mo","ui"]},{"label":"hut_mo","text":["hut","mo","toan"]},{"label":"hut_mo","text":["giam","beo","khong","phau","thuat"]},{"label":"hut_mo","text":["hut","mo","bodi"]},{"label":"hut_mo","text":["hut","mo","bap","tai"]},{"label":"hut_mo","text":["giam","mo","nhanh"]},{"label":"hut_mo","text":["hut","mo","co","au","khong"]},{"label":"tham_my_vung_kin","text":["thu","hep","vung","kin"]},{"label":"tham_my_vung_kin","text":["tu","van","tham","vung","kin"]},{"label":"tham_my_vung_kin","text":["phau","thuat","vung","kin"]},{"label":"tham_my_vung_kin","text":["lam","hong","vung","kin"]},{"label":"tham_my_vung_kin","text":["tao","hinh","vung","kin"]},{"label":"xem_feedback","text":["xem","ket","qua"]},{"label":"xem_feedback","text":["hinh","anh","truoc","sau"]},{"label":"xem_feedback","text":["khach","hang","lam"]},{"label":"xem_feedback","text":["review","ket","qua"]},{"label":"xem_feedback","text":["feedback","khach","hang"]},{"label":"xem_feedback","text":["ket","qua","tham"]},{"label":"xem_feedback","text":["hinh","anh","thuc","te"]},{"label":"bien_chung","text":["bien","chung"]},{"label":"bien_chung","text":["bi","bien","chung"]},{"label":"bien_chung","text":["co","bien","chung"]},{"label":"nang_mui","text":["nang","mui","het","bao","nhieu"]},{"label":"nang_mui","text":["tu","van","nang","mui"]},{"label":"nang_mui","text":["phau","thuat","mui"]},{"label":"nang_mui","text":["muon","sua","mui"]},{"label":"nang_mui","text":["nang","mui","sun","suon"]},{"label":"nang_mui","text":["nang","mui","co","au","khong"]},{"label":"nang_mui","text":["cho","em","hoi","ve","nang","mui"]},{"label":"nang_mui","text":["muon","nang","mui"]},{"label":"nang_mui","text":["tu","van","ve","mui"]},{"label":"nang_mui","text":["phau","thuat","nang","mui"]},{"label":"nang_mui","text":["nang","mui","tham"]},{"label":"nang_mui","text":["lam","mui"]},{"label":"tham_my_mat","text":["bac","si","tu","van","cat","mi","giup","em"]},{"label":"tham_my_mat","text":["tu","van","ve","mat"]},{"label":"bien_chung","text":["bi","ch","ng"]},{"label":"bien_chung","text":["bi","ch","ng"]},{"label":"bien_chung","text":["bi","ch","ng"]},{"label":"bien_chung","text":["bi","ch","ng"]},{"label":"bien_chung","text":["bi","ch","ng","ph","thu"]},{"label":"bien_chung","text":["bi","ch","ng","th"]},{"label":"bien_chung","text":["bi","ch","ng","sau","ph","thu"]},{"label":"bien_chung","text":["bi","ch","ng"]},{"label":"bien_chung","text":["bi","ch","ng"]},{"label":"bien_chung","text":["lo","bi","ch","ng"]},{"label":"bien_chung","text":["bi","ch","ng"]},{"label":"bien_chung","text":["ng"]},{"label":"bien_chung","text":["ng"]},{"label":"bien_chung","text":["ng","ng"]},{"label":"bien_chung","text":["bi","ng"]},{"label":"bien_chung","text":["ph","thu"]},{"label":"bien_chung","text":["ch","nh"]},{"label":"bien_chung","text":["kh","ph"]},{"label":"bien_chung","text":["gi"]},{"label":"treo_sa_tre","text":["sa","tr"]},{"label":"treo_sa_tre","text":["ng","sa"]},{"label":"treo_sa_tre","text":["ng","tr"]},{"label":"treo_sa_tre","text":["sa","tr","ng"]},{"label":"treo_sa_tre","text":["treo","ng","sa"]},{"label":"treo_sa_tre","text":["treo","sa"]},{"label":"treo_sa_tre","text":["treo","ng"]},{"label":"treo_sa_tre","text":["ph","thu","sa","tr"]},{"label":"cang_da","text":["ng","da"]},{"label":"cang_da","text":["ng","da"]},{"label":"cang_da","text":["ng","ch"]},{"label":"cang_da","text":["ng","ch"]},{"label":"treo_sa_tre","text":["ng","ng","sa","tr"]},{"label":"treo_sa_tre","text":["ph","thu","treo","ng"]},{"label":"treo_sa_tre","text":["kh","ph","ng","sa"]},{"label":"treo_sa_tre","text":["kh","ph","ng","tr"]},{"label":"bien_chung","text":["ch","nh"]},{"label":"bien_chung","text":["kh","ph"]},{"label":"bien_chung","text":["gi"]},{"label":"faq_thao_tui","text":["th","ng"]},{"label":"faq_thao_tui","text":["th","kh","ng","au"]},{"label":"faq_nang_nguc_dao","text":["ng","ng","dao","si"]},{"label":"faq_nang_nguc_dao","text":["ng","ng","kh","ng","au"]},{"label":"faq_nguc_bay","text":["bai","sau","ng","ng"]},{"label":"faq_nguc_bay","text":["bai","sau","ng","ng"]},{"label":"faq_nguc_bay","text":["xu","vi","sau","ng","ng"]},{"label":"bien_chung","text":["ch","nh"]},{"label":"bien_chung","text":["kh","ph"]},{"label":"bien_chung","text":["gi"]}],"features":{"xem":2,"cac":3,"dich":11,"vu":11,"menu":2,"khac":2,"lam":10,"ep":5,"dv":4,"tham":6,"tu":18,"van":19,"co":7,"nhung":1,"nao":2,"danh":1,"sach":1,"gi":6,"muon":10,"tat":1,"ca":2,"nang":18,"nguc":10,"gia":4,"bao":5,"nhieu":4,"phau":8,"thuat":8,"au":11,"khong":7,"chi":12,"phi":3,"tui":3,"tot":1,"lai":1,"seo":1,"lau":1,"thi":1,"lanh":1,"thao":1,"cu":1,"thai":1,"mui":22,"het":2,"sua":5,"sun":2,"suon":2,"chinh":3,"hong":3,"bi":16,"lech":2,"bien":4,"chung":4,"cat":2,"mi":5,"mat":10,"nhan":2,"bam":1,"ve":4,"xe":2,"mot":1,"eu":1,"treo":5,"cung":1,"mai":1,"cam":6,"ngan":1,"vline":1,"cang":4,"da":6,"tre":1,"hoa":1,"chai":1,"xoa":1,"bang":1,"lich":8,"hen":3,"kham":12,"ang":1,"ky":1,"gap":2,"bac":3,"si":4,"cho":5,"em":11,"xin":6,"ien":8,"thoai":8,"zalo":5,"viber":3,"truc":2,"tiep":2,"en":3,"uoc":1,"giup":2,"book":2,"cua":12,"la":10,"sdt":1,"ay":2,"phong":7,"ia":3,"iem":1,"nam":1,"tim":1,"uong":2,"hut":6,"mo":8,"bung":2,"giam":3,"ui":1,"toan":1,"beo":1,"bodi":1,"bap":1,"tai":1,"nhanh":1,"thu":6,"hep":1,"vung":5,"kin":5,"tao":1,"hinh":3,"ket":3,"qua":3,"anh":2,"truoc":1,"sau":5,"khach":2,"hang":2,"review":1,"feedback":1,"thuc":1,"te":1,"hoi":1,"ch":16,"ng":43,"ph":10,"th":3,"lo":1,"nh":3,"kh":7,"sa":8,"tr":6,"dao":1,"bai":2,"xu":1,"vi":1},"stemmer":{},"lastAdded":203,"events":{"_events":{},"_eventsCount":0}}
{
  "classifier":{
    "classFeatures":{
      "menu_dich_vu":{
        "0":2,
        "1":4,
        "2":12,
        "3":12,
        "4":3,
        "5":3,
        "6":6,
        "7":6,
        "8":5,
        "9":4,
        "10":3,
        "11":3,
        "12":2,
        "13":2,
        "14":2,
        "15":2,
        "16":2,
        "17":4,
        "18":2,
        "19":2,
        "20":2
      },
      "nang_nguc":{
        "10":2,
        "11":2,
        "12":3,
        "18":2,
        "21":7,
        "22":11,
        "23":2,
        "24":3,
        "25":2,
        "26":2,
        "27":2,
        "28":3,
        "29":3,
        "30":2,
        "31":2,
        "32":4,
        "33":2,
        "34":2,
        "35":2,
        "36":2,
        "37":2,
        "38":2,
        "39":2,
        "40":2,
        "41":2
      },
      "nang_mui":{
        "6":2,
        "9":2,
        "10":4,
        "11":4,
        "12":3,
        "18":4,
        "21":13,
        "24":3,
        "25":3,
        "26":4,
        "27":4,
        "28":3,
        "29":3,
        "42":23,
        "43":3,
        "44":5,
        "45":3,
        "46":3,
        "47":2,
        "48":3,
        "49":3,
        "50":2,
        "51":2,
        "52":2,
        "58":3,
        "83":2,
        "84":2,
        "134":2
      },
      "tham_my_mat":{
        "10":4,
        "11":4,
        "26":2,
        "27":2,
        "29":2,
        "44":2,
        "47":2,
        "49":2,
        "53":3,
        "54":6,
        "55":9,
        "56":2,
        "57":2,
        "58":3,
        "59":2,
        "60":2,
        "61":2,
        "62":2,
        "63":2,
        "64":2,
        "81":2,
        "82":2,
        "84":2,
        "94":2
      },
      "tham_my_cam":{
        "6":2,
        "47":2,
        "50":2,
        "65":7,
        "66":2,
        "67":2
      },
      "cang_da":{
        "6":2,
        "30":2,
        "55":3,
        "56":2,
        "59":2,
        "68":5,
        "69":7,
        "70":2,
        "71":2,
        "72":2,
        "73":2,
        "135":3,
        "136":5
      },
      "hoi_gia":{
        "14":2,
        "20":2,
        "23":4,
        "24":2,
        "25":2,
        "26":2,
        "27":2,
        "30":2,
        "31":3,
        "74":2
      },
      "dat_lich":{
        "10":9,
        "11":9,
        "18":6,
        "30":7,
        "75":9,
        "76":4,
        "77":6,
        "78":2,
        "79":2,
        "80":3,
        "81":2,
        "82":2,
        "83":4,
        "84":10,
        "85":7,
        "86":9,
        "87":9,
        "88":6,
        "89":4,
        "90":3,
        "91":3,
        "92":2,
        "93":2,
        "94":2,
        "95":3,
        "96":13,
        "97":11,
        "98":2,
        "99":3
      },
      "dia_chi":{
        "11":2,
        "28":5,
        "30":4,
        "77":8,
        "81":2,
        "82":2,
        "83":2,
        "92":3,
        "100":8,
        "101":4,
        "102":2,
        "103":2,
        "104":2,
        "105":3
      },
      "hut_mo":{
        "12":2,
        "26":2,
        "27":2,
        "28":2,
        "29":3,
        "106":7,
        "107":9,
        "108":3,
        "109":4,
        "110":2,
        "111":2,
        "112":2,
        "113":2,
        "114":2,
        "115":2,
        "116":2
      },
      "tham_my_vung_kin":{
        "6":2,
        "9":2,
        "10":2,
        "11":2,
        "26":2,
        "27":2,
        "48":2,
        "117":2,
        "118":2,
        "119":6,
        "120":6,
        "121":2,
        "122":2
      },
      "xem_feedback":{
        "0":2,
        "6":2,
        "9":2,
        "122":3,
        "123":4,
        "124":4,
        "125":3,
        "126":2,
        "127":2,
        "128":3,
        "129":3,
        "130":2,
        "131":2,
        "132":2,
        "133":2
      },
      "bien_chung":{
        "12":2,
        "17":4,
        "49":14,
        "51":4,
        "52":4,
        "117":4,
        "127":2,
        "135":15,
        "136":16,
        "137":7,
        "138":2,
        "139":2,
        "140":4,
        "141":4
      },
      "treo_sa_tre":{
        "62":5,
        "117":3,
        "136":10,
        "137":5,
        "141":3,
        "142":9,
        "143":7
      },
      "faq_thao_tui":{
        "28":2,
        "136":3,
        "138":3,
        "141":2
      },
      "faq_nang_nguc_dao":{
        "28":2,
        "82":2,
        "136":3,
        "141":2,
        "144":2
      },
      "faq_nguc_bay":{
        "127":4,
        "136":4,
        "145":3,
        "146":2,
        "147":2
      },
      "classTotals":{
        "menu_dich_vu":21,
        "nang_nguc":11,
        "nang_mui":23,
        "tham_my_mat":13,
        "tham_my_cam":7,
        "cang_da":11,
        "hoi_gia":6,
        "dat_lich":42,
        "dia_chi":10,
        "hut_mo":10,
        "tham_my_vung_kin":6,
        "xem_feedback":8,
        "bien_chung":29,
        "treo_sa_tre":13,
        "faq_thao_tui":3,
        "faq_nang_nguc_dao":3,
        "faq_nguc_bay":4,
        "faq_size_tui": 8
      },
      "totalExamples":204,
      "smoothing":1
    },
    "docs":[
      {"label":"menu_dich_vu","text":["xem","cac","dich","vu"]},
      {"label":"menu_dich_vu","text":["menu","dich","vu"]},
      {"label":"menu_dich_vu","text":["cac","dich","vu","khac"]},
      {"label":"menu_dich_vu","text":["dich","vu","lam","ep"]},
      {"label":"menu_dich_vu","text":["dv","lam","ep"]},
      {"label":"menu_dich_vu","text":["dich","vu","tham"]},
      {"label":"menu_dich_vu","text":["tu","van","dich","vu"]},
      {"label":"menu_dich_vu","text":["co","nhung","dich","vu","nao"]},
      {"label":"menu_dich_vu","text":["danh","sach","dich","vu"]},
      {"label":"menu_dich_vu","text":["dich","vu","gi"]},
      {"label":"menu_dich_vu","text":["tham","gi"]},
      {"label":"menu_dich_vu","text":["lam","ep","gi"]},
      {"label":"menu_dich_vu","text":["menu"]},
      {"label":"menu_dich_vu","text":["dich","vu"]},
      {"label":"menu_dich_vu","text":["tu","van","lam","ep"]},
      {"label":"menu_dich_vu","text":["muon","lam","ep"]},
      {"label":"menu_dich_vu","text":["dv","tham"]},
      {"label":"menu_dich_vu","text":["dv","khac"]},
      {"label":"menu_dich_vu","text":["cac","dv"]},
      {"label":"menu_dich_vu","text":["tat","ca","dich","vu"]},
      {"label":"nang_nguc","text":["tu","van","nang","nguc"]},
      {"label":"nang_nguc","text":["nang","nguc","gia","bao","nhieu"]},
      {"label":"nang_nguc","text":["phau","thuat","nguc","co","au","khong"]},
      {"label":"nang_nguc","text":["muon","nang","nguc"]},
      {"label":"nang_nguc","text":["chi","phi","tui","nguc"]},
      {"label":"nang_nguc","text":["nang","nguc","au","tot"]},
      {"label":"nang_nguc","text":["nang","nguc","co","lai","seo","khong"]},
      {"label":"nang_nguc","text":["nang","nguc","bao","lau","thi","lanh"]},
      {"label":"nang_nguc","text":["thao","tui","nguc","cu"]},
      {"label":"nang_nguc","text":["thai","tui","nguc"]},
      {"label":"nang_mui","text":["nang","mui","het","bao","nhieu"]},
      {"label":"nang_mui","text":["tu","van","nang","mui"]},
      {"label":"nang_mui","text":["phau","thuat","mui"]},
      {"label":"nang_mui","text":["muon","sua","mui"]},
      {"label":"nang_mui","text":["nang","mui","sun","suon"]},
      {"label":"nang_mui","text":["nang","mui","co","au","khong"]},
      {"label":"nang_mui","text":["chinh","sua","mui","hong"]},
      {"label":"nang_mui","text":["mui","bi","lech"]},
      {"label":"nang_mui","text":["mui","bi","bien","chung"]},
      {"label":"nang_mui","text":["sua","mui","hong"]},
      {"label":"tham_my_mat","text":["cat","mi","mat"]},
      {"label":"tham_my_mat","text":["nhan","mi"]},
      {"label":"tham_my_mat","text":["bam","mi"]},
      {"label":"tham_my_mat","text":["tu","van","ve","mat"]},
      {"label":"tham_my_mat","text":["phau","thuat","mat"]},
      {"label":"tham_my_mat","text":["mat","bi","xe"]},
      {"label":"tham_my_mat","text":["mat","mot","mi"]},
      {"label":"tham_my_mat","text":["mat","khong","eu"]},
      {"label":"tham_my_mat","text":["treo","cung","mai"]},
      {"label":"tham_my_mat","text":["chinh","sua","mat"]},
      {"label":"tham_my_cam","text":["cam"]},
      {"label":"tham_my_cam","text":["cam"]},
      {"label":"tham_my_cam","text":["cam","ngan"]},
      {"label":"tham_my_cam","text":["cam","lech"]},
      {"label":"tham_my_cam","text":["chinh","cam"]},
      {"label":"tham_my_cam","text":["lam","cam","vline"]},
      {"label":"cang_da","text":["cang","da","mat"]},
      {"label":"cang_da","text":["tre","hoa","da"]},
      {"label":"cang_da","text":["cang","chi"]},
      {"label":"cang_da","text":["cang","da","chai","xe"]},
      {"label":"cang_da","text":["xoa","nhan"]},
      {"label":"cang_da","text":["lam","cang","da","mat"]},
      {"label":"hoi_gia","text":["gia","bao","nhieu"]},
      {"label":"hoi_gia","text":["chi","phi"]},
      {"label":"hoi_gia","text":["bang","gia"]},
      {"label":"hoi_gia","text":["phi","phau","thuat"]},
      {"label":"hoi_gia","text":["gia","ca","nao"]},
      {"label":"dat_lich","text":["lich"]},
      {"label":"dat_lich","text":["hen","kham"]},
      {"label":"dat_lich","text":["ang","ky","tu","van"]},
      {"label":"dat_lich","text":["muon","gap","bac","si"]},
      {"label":"dat_lich","text":["lich","kham"]},
      {"label":"dat_lich","text":["cho","em","xin","ien","thoai"]},
      {"label":"dat_lich","text":["xin","zalo"]},
      {"label":"dat_lich","text":["xin","viber"]},
      {"label":"dat_lich","text":["muon","tu","van"]},
      {"label":"dat_lich","text":["tu","van","truc","tiep"]},
      {"label":"dat_lich","text":["gap","truc","tiep"]},
      {"label":"dat_lich","text":["muon","en","kham"]},
      {"label":"dat_lich","text":["hen"]},
      {"label":"dat_lich","text":["xin","ien","thoai","tu","van"]},
      {"label":"dat_lich","text":["muon","uoc","tu","van"]},
      {"label":"dat_lich","text":["tu","van"]},
      {"label":"dat_lich","text":["tu","van","giup","em"]},
      {"label":"dat_lich","text":["cho","em","lich"]},
      {"label":"dat_lich","text":["muon","book","lich"]},
      {"label":"dat_lich","text":["book","lich","kham"]},
      {"label":"dat_lich","text":["lich"]},
      {"label":"dat_lich","text":["hen"]},
      {"label":"dat_lich","text":["lich","kham"]},
      {"label":"dat_lich","text":["lich","tu","van"]},
      {"label":"dat_lich","text":["xin","ien","thoai"]},
      {"label":"dat_lich","text":["cho","xin","ien","thoai"]},
      {"label":"dat_lich","text":["ien","thoai","cua","chi","la"]},
      {"label":"dat_lich","text":["ien","thoai","cua","em","la"]},
      {"label":"dat_lich","text":["cua","chi","la"]},
      {"label":"dat_lich","text":["cua","em","la"]},
      {"label":"dat_lich","text":["ien","thoai"]},
      {"label":"dat_lich","text":["sdt"]},
      {"label":"dat_lich","text":["ien","thoai"]},
      {"label":"dat_lich","text":["ay","la","cua","chi"]},
      {"label":"dat_lich","text":["ay","la","cua","em"]},
      {"label":"dat_lich","text":["zalo","cua","chi","la"]},
      {"label":"dat_lich","text":["zalo","cua","em","la"]},
      {"label":"dat_lich","text":["zalo","cua","chi"]},
      {"label":"dat_lich","text":["zalo","cua","em"]},
      {"label":"dat_lich","text":["viber","cua","chi","la"]},
      {"label":"dat_lich","text":["viber","cua","em","la"]},
      {"label":"dia_chi","text":["phong","kham","au"]},
      {"label":"dia_chi","text":["ia","chi","phong","kham"]},
      {"label":"dia_chi","text":["cho","kham","au"]},
      {"label":"dia_chi","text":["ia","iem","phong","kham"]},
      {"label":"dia_chi","text":["van","phong","au"]},
      {"label":"dia_chi","text":["ia","chi","bac","si"]},
      {"label":"dia_chi","text":["phong","kham","nam","au"]},
      {"label":"dia_chi","text":["tim","uong","en","phong","kham"]},
      {"label":"dia_chi","text":["chi","uong","en","phong","kham"]},
      {"label":"hut_mo","text":["hut","mo","bung"]},
      {"label":"hut_mo","text":["giam","mo","bung"]},
      {"label":"hut_mo","text":["hut","mo","ui"]},
      {"label":"hut_mo","text":["hut","mo","toan"]},
      {"label":"hut_mo","text":["giam","beo","khong","phau","thuat"]},
      {"label":"hut_mo","text":["hut","mo","bodi"]},
      {"label":"hut_mo","text":["hut","mo","bap","tai"]},
      {"label":"hut_mo","text":["giam","mo","nhanh"]},
      {"label":"hut_mo","text":["hut","mo","co","au","khong"]},
      {"label":"tham_my_vung_kin","text":["thu","hep","vung","kin"]},
      {"label":"tham_my_vung_kin","text":["tu","van","tham","vung","kin"]},
      {"label":"tham_my_vung_kin","text":["phau","thuat","vung","kin"]},
      {"label":"tham_my_vung_kin","text":["lam","hong","vung","kin"]},
      {"label":"tham_my_vung_kin","text":["tao","hinh","vung","kin"]},
      {"label":"xem_feedback","text":["xem","ket","qua"]},
      {"label":"xem_feedback","text":["hinh","anh","truoc","sau"]},
      {"label":"xem_feedback","text":["khach","hang","lam"]},
      {"label":"xem_feedback","text":["review","ket","qua"]},
      {"label":"xem_feedback","text":["feedback","khach","hang"]},
      {"label":"xem_feedback","text":["ket","qua","tham"]},
      {"label":"xem_feedback","text":["hinh","anh","thuc","te"]},
      {"label":"bien_chung","text":["bien","chung"]},
      {"label":"bien_chung","text":["bi","bien","chung"]},
      {"label":"bien_chung","text":["co","bien","chung"]},
      {"label":"nang_mui","text":["nang","mui","het","bao","nhieu"]},
      {"label":"nang_mui","text":["tu","van","nang","mui"]},
      {"label":"nang_mui","text":["phau","thuat","mui"]},
      {"label":"nang_mui","text":["muon","sua","mui"]},
      {"label":"nang_mui","text":["nang","mui","sun","suon"]},
      {"label":"nang_mui","text":["nang","mui","co","au","khong"]},
      {"label":"nang_mui","text":["cho","em","hoi","ve","nang","mui"]},
      {"label":"nang_mui","text":["muon","nang","mui"]},
      {"label":"nang_mui","text":["tu","van","ve","mui"]},
      {"label":"nang_mui","text":["phau","thuat","nang","mui"]},
      {"label":"nang_mui","text":["nang","mui","tham"]},
      {"label":"nang_mui","text":["lam","mui"]},
      {"label":"tham_my_mat","text":["bac","si","tu","van","cat","mi","giup","em"]},
      {"label":"tham_my_mat","text":["tu","van","ve","mat"]},
      {"label":"bien_chung","text":["bi","ch","ng"]},
      {"label":"bien_chung","text":["bi","ch","ng"]},
      {"label":"bien_chung","text":["bi","ch","ng"]},
      {"label":"bien_chung","text":["bi","ch","ng"]},
      {"label":"bien_chung","text":["bi","ch","ng","ph","thu"]},
      {"label":"bien_chung","text":["bi","ch","ng","th"]},
      {"label":"bien_chung","text":["bi","ch","ng","sau","ph","thu"]},
      {"label":"bien_chung","text":["bi","ch","ng"]},
      {"label":"bien_chung","text":["bi","ch","ng"]},
      {"label":"bien_chung","text":["lo","bi","ch","ng"]},
      {"label":"bien_chung","text":["bi","ch","ng"]},
      {"label":"bien_chung","text":["ng"]},
      {"label":"bien_chung","text":["ng"]},
      {"label":"bien_chung","text":["ng","ng"]},
      {"label":"bien_chung","text":["bi","ng"]},
      {"label":"bien_chung","text":["ph","thu"]},
      {"label":"bien_chung","text":["ch","nh"]},
      {"label":"bien_chung","text":["kh","ph"]},
      {"label":"bien_chung","text":["gi"]},
      {"label":"treo_sa_tre","text":["sa","tr"]},
      {"label":"treo_sa_tre","text":["ng","sa"]},
      {"label":"treo_sa_tre","text":["ng","tr"]},
      {"label":"treo_sa_tre","text":["sa","tr","ng"]},
      {"label":"treo_sa_tre","text":["treo","ng","sa"]},
      {"label":"treo_sa_tre","text":["treo","sa"]},
      {"label":"treo_sa_tre","text":["treo","ng"]},
      {"label":"treo_sa_tre","text":["ph","thu","sa","tr"]},
      {"label":"cang_da","text":["ng","da"]},
      {"label":"cang_da","text":["ng","da"]},
      {"label":"cang_da","text":["ng","ch"]},
      {"label":"cang_da","text":["ng","ch"]},
      {"label":"treo_sa_tre","text":["ng","ng","sa","tr"]},
      {"label":"treo_sa_tre","text":["ph","thu","treo","ng"]},
      {"label":"treo_sa_tre","text":["kh","ph","ng","sa"]},
      {"label":"treo_sa_tre","text":["kh","ph","ng","tr"]},
      {"label":"bien_chung","text":["ch","nh"]},
      {"label":"bien_chung","text":["kh","ph"]},
      {"label":"bien_chung","text":["gi"]},
      {"label":"faq_thao_tui","text":["th","ng"]},
      {"label":"faq_thao_tui","text":["th","kh","ng","au"]},
      {"label":"faq_nang_nguc_dao","text":["ng","ng","dao","si"]},
      {"label":"faq_nang_nguc_dao","text":["ng","ng","kh","ng","au"]},
      {"label":"faq_nguc_bay","text":["bai","sau","ng","ng"]},
      {"label":"faq_nguc_bay","text":["bai","sau","ng","ng"]},
      {"label":"faq_nguc_bay","text":["xu","vi","sau","ng","ng"]},
      {"label":"bien_chung","text":["ch","nh"]},
      {"label":"bien_chung","text":["kh","ph"]},
      {"label":"bien_chung","text":["gi"]}],"features":{"xem":2,"cac":3,"dich":11,"vu":11,"menu":2,"khac":2,"lam":10,"ep":5,"dv":4,"tham":6,"tu":18,"van":19,"co":7,"nhung":1,"nao":2,"danh":1,"sach":1,"gi":6,"muon":10,"tat":1,"ca":2,"nang":18,"nguc":10,"gia":4,"bao":5,"nhieu":4,"phau":8,"thuat":8,"au":11,"khong":7,"chi":12,"phi":3,"tui":3,"tot":1,"lai":1,"seo":1,"lau":1,"thi":1,"lanh":1,"thao":1,"cu":1,"thai":1,"mui":22,"het":2,"sua":5,"sun":2,"suon":2,"chinh":3,"hong":3,"bi":16,"lech":2,"bien":4,"chung":4,"cat":2,"mi":5,"mat":10,"nhan":2,"bam":1,"ve":4,"xe":2,"mot":1,"eu":1,"treo":5,"cung":1,"mai":1,"cam":6,"ngan":1,"vline":1,"cang":4,"da":6,"tre":1,"hoa":1,"chai":1,"xoa":1,"bang":1,"lich":8,"hen":3,"kham":12,"ang":1,"ky":1,"gap":2,"bac":3,"si":4,"cho":5,"em":11,"xin":6,"ien":8,"thoai":8,"zalo":5,"viber":3,"truc":2,"tiep":2,"en":3,"uoc":1,"giup":2,"book":2,"cua":12,"la":10,"sdt":1,"ay":2,"phong":7,"ia":3,"iem":1,"nam":1,"tim":1,"uong":2,"hut":6,"mo":8,"bung":2,"giam":3,"ui":1,"toan":1,"beo":1,"bodi":1,"bap":1,"tai":1,"nhanh":1,"thu":6,"hep":1,"vung":5,"kin":5,"tao":1,"hinh":3,"ket":3,"qua":3,"anh":2,"truoc":1,"sau":5,"khach":2,"hang":2,"review":1,"feedback":1,"thuc":1,"te":1,"hoi":1,"ch":16,"ng":43,"ph":10,"th":3,"lo":1,"nh":3,"kh":7,"sa":8,"tr":6,"dao":1,"bai":2,"xu":1,"vi":1},"stemmer":{},"lastAdded":203,"events":{"_events":{},"_eventsCount":0}},
      {"label": "faq_size_tui", "text": ["size", "nguc"]},
      {"label": "faq_size_tui", "text": ["size", "tui", "nguc"]},
      {"label": "faq_size_tui", "text": ["size", "nao"]},
      {"label": "faq_size_tui", "text": ["size", "bao", "nhieu"]},
      {"label": "faq_size_tui", "text": ["kich", "thuoc", "tui"]},
      {"label": "faq_size_tui", "text": ["kich", "thuoc", "nguc"]},
      {"label": "faq_size_tui", "text": ["chon", "size", "nao"]},
      {"label": "faq_size_tui", "text": ["size", "phu", "hop"]}